dwclib/__init__.py
dwclib/alerts/__init__.py
dwclib/alerts/alerts.py
dwclib/assets/__init__.py
dwclib/assets/alert_ref.csv
dwclib/common/db.py
dwclib/common/meta.py
dwclib/common/numerics.py
dwclib/common/wave_unfold.py
dwclib/common/waves.py
dwclib/dask/__init__.py
dwclib/dask/generic.py
dwclib/dask/numerics.py
dwclib/dask/waves.py
dwclib/dask/waves_convert.py
dwclib/enumerations/__init__.py
dwclib/enumerations/enumerations.py
dwclib/numerics/__init__.py
dwclib/numerics/numerics.py
dwclib/patients/__init__.py
dwclib/patients/patients.py
dwclib/waves/__init__.py
dwclib/waves/waves.py
dwclib-2025.12.5.dist-info/METADATA
dwclib-2025.12.5.dist-info/WHEEL
dwclib-2025.12.5.dist-info/licenses/LICENSE
dwclib-2025.12.5.dist-info/RECORD
