Metadata-Version: 2.4
Name: dwclib
Version: 2025.12.5
Summary: Python wrapper to DataWarehouse Connect
License: ISC
License-File: LICENSE
Author: Jona Joachim
Author-email: jona@joachim.cc
Requires-Python: >=3.10,<4.0
Classifier: License :: OSI Approved
Classifier: Programming Language :: Python :: 3
Classifier: Programming Language :: Python :: 3.10
Classifier: Programming Language :: Python :: 3.11
Classifier: Programming Language :: Python :: 3.12
Classifier: Programming Language :: Python :: 3.13
Classifier: Programming Language :: Python :: 3.14
Provides-Extra: dwcmeta
Requires-Dist: SQLAlchemy (>=2,<3)
Requires-Dist: dask[dataframe] (>=2024.4.1,<2025.0.0)
Requires-Dist: numpy (>=2,<3)
Requires-Dist: pandas (>=2,<3)
Requires-Dist: platformdirs (>=3,<4)
Requires-Dist: psycopg[binary] (>=3.2.3,<4.0.0) ; extra == "dwcmeta"
Requires-Dist: pyarrow (>=14)
Requires-Dist: pymssql (>=2.3,<3.0)
Project-URL: Repository, https://github.com/larib-data/dwclib
